MANIFEST.in
README.md
setup.py
up.txt
shacrypt/__init__.py
shacrypt.egg-info/PKG-INFO
shacrypt.egg-info/SOURCES.txt
shacrypt.egg-info/dependency_links.txt
shacrypt.egg-info/top_level.txt